LICENSE
README.md
setup.cfg
setup.py
ptcq/__init__.py
ptcq/ptcq.py
ptcq.egg-info/PKG-INFO
ptcq.egg-info/SOURCES.txt
ptcq.egg-info/dependency_links.txt
ptcq.egg-info/requires.txt
ptcq.egg-info/top_level.txt