Metadata-Version: 1.1
Name: ptcq
Version: 0.1.1
Summary: PyTorch Complex Quantization
Home-page: https://github.com/Teddy-van-Jerry/ptcq
Author: Teddy van Jerry (Wuqiong Zhao)
Author-email: me@teddy-van-jerry.org
License: UNKNOWN
Platform: UNKNOWN
Classifier: Development Status :: 4 - Beta
Classifier: Intended Audience :: Developers
Classifier: License :: OSI Approved :: MIT License
Classifier: Programming Language :: Python :: 3
Classifier: Programming Language :: Python :: 3.6
Classifier: Programming Language :: Python :: 3.7
Classifier: Programming Language :: Python :: 3.8
Classifier: Programming Language :: Python :: 3.9
Classifier: Programming Language :: Python :: 3.10
Classifier: Programming Language :: Python :: 3.11
